ubuntu_termux/__init__.py
ubuntu_termux/install.py
ubuntu_termux/start.py
ubuntu_termux-0.0.4.1.dist-info/LICENSE
ubuntu_termux-0.0.4.1.dist-info/METADATA
ubuntu_termux-0.0.4.1.dist-info/WHEEL
ubuntu_termux-0.0.4.1.dist-info/entry_points.txt
ubuntu_termux-0.0.4.1.dist-info/top_level.txt
ubuntu_termux-0.0.4.1.dist-info/RECORD
