Metadata-Version: 2.1
Name: ubuntu-termux
Version: 0.0.4.1
Summary: install and use the Ubuntu on the Termux
Home-page: https://github.com/perseu912/ubuntu-termux
Author: Reinan Br
Author-email: slimchatuba@gmail.com
License: GPLv3
Keywords: ubuntu termux linux
License-File: LICENSE
Requires-Dist: kitano
